eeglib/__init__.py
eeglib/auxFunctions.py
eeglib/eeg.py
eeglib/features.py
eeglib/helpers.py
eeglib/preprocessing.py
eeglib/wrapper.py
eeglib-0.4.1.1.dist-info/LICENSE.txt
eeglib-0.4.1.1.dist-info/METADATA
eeglib-0.4.1.1.dist-info/WHEEL
eeglib-0.4.1.1.dist-info/top_level.txt
eeglib-0.4.1.1.dist-info/RECORD
