Metadata-Version: 2.1
Name: eeglib
Version: 0.4.1.1
Summary: A library with some tools and functions for EEG signal analysis
Home-page: https://github.com/Xiul109/eeglib
Author: Luis Cabañero Gómez
Author-email: Luis.Cabanero@uclm.es
License: MIT
Keywords: lib EEG signal analysis
Platform: UNKNOWN
Classifier: Development Status :: 4 - Beta
Classifier: Intended Audience :: Developers
Classifier: Intended Audience :: Science/Research
Classifier: License :: OSI Approved :: MIT License
Classifier: Programming Language :: Python :: 3.6
Classifier: Topic :: Scientific/Engineering
License-File: LICENSE.txt
Requires-Dist: fastdtw
Requires-Dist: numba
Requires-Dist: numpy
Requires-Dist: pandas
Requires-Dist: progressbar2
Requires-Dist: pyedflib
Requires-Dist: scikit-learn
Requires-Dist: scipy
Provides-Extra: doc
Requires-Dist: numpydoc ; extra == 'doc'
Requires-Dist: sphinx ; extra == 'doc'
